tracemoe/__init__.py
tracemoe_py-1.0.3.dist-info/LICENSE
tracemoe_py-1.0.3.dist-info/METADATA
tracemoe_py-1.0.3.dist-info/WHEEL
tracemoe_py-1.0.3.dist-info/top_level.txt
tracemoe_py-1.0.3.dist-info/RECORD
