Metadata-Version: 2.1
Name: tracemoe-py
Version: 1.0.3
Summary: A minimal asynchronous API wrapper for trace.moe
Home-page: https://github.com/IchBinLeoon/tracemoe-py
Author: IchBinLeoon
License: MIT
Project-URL: Issue tracker, https://github.com/IchBinLeoon/tracemoe-py/issues
Platform: UNKNOWN
Classifier: Development Status :: 5 - Production/Stable
Classifier: License :: OSI Approved :: MIT License
Classifier: Intended Audience :: Developers
Classifier: Natural Language :: English
Classifier: Operating System :: OS Independent
Classifier: Programming Language :: Python :: 3
Classifier: Programming Language :: Python :: 3.6
Classifier: Programming Language :: Python :: 3.7
Classifier: Programming Language :: Python :: 3.8
Classifier: Programming Language :: Python :: 3.9
Classifier: Topic :: Internet
Classifier: Topic :: Software Development :: Libraries
Classifier: Topic :: Software Development :: Libraries :: Python Modules
Classifier: Topic :: Utilities
Requires-Python: >=3.6
License-File: LICENSE
Requires-Dist: aiohttp
